assertion/__init__.py
assertion/assertion.py
assertion/deco.py
assertion/deferred_info.py
assertion-1.0.0.dist-info/WHEEL
assertion-1.0.0.dist-info/METADATA
assertion-1.0.0.dist-info/LICENSE.md
assertion-1.0.0.dist-info/RECORD
