Metadata-Version: 2.1
Name: assertion
Version: 1.0.0
Summary: Supercharged assertion tests
License: MIT
Keywords: assert,testing
Author-email: COHERENT MINDS Team <dev@coherentminds.de>
Requires-Python: >=3.7
Classifier: Development Status :: 5 - Production/Stable
Classifier: Intended Audience :: Developers
Classifier: License :: OSI Approved :: MIT License
Classifier: Programming Language :: Python :: 3.10
Classifier: Programming Language :: Python :: 3.7
Classifier: Programming Language :: Python :: 3.8
Classifier: Programming Language :: Python :: 3.9
Classifier: Topic :: Software Development :: Testing
Project-URL: COHERENT MINDS, https://coherentminds.de/
Project-URL: Repository, https://gitlab.com/coherentminds/assertion/
